LICENSE
MANIFEST.in
README.rst
requirements.txt
setup.py
accordion_presentation/__init__.py
accordion_presentation/admin.py
accordion_presentation/cms_app.py
accordion_presentation/cms_plugins.py
accordion_presentation/models.py
accordion_presentation/tests.py
accordion_presentation/urls.py
accordion_presentation/views.py
accordion_presentation.egg-info/PKG-INFO
accordion_presentation.egg-info/SOURCES.txt
accordion_presentation.egg-info/dependency_links.txt
accordion_presentation.egg-info/not-zip-safe
accordion_presentation.egg-info/requires.txt
accordion_presentation.egg-info/top_level.txt
accordion_presentation/locale/es/LC_MESSAGES/django.mo
accordion_presentation/locale/es/LC_MESSAGES/django.po
accordion_presentation/migrations/0001_initial.py
accordion_presentation/migrations/__init__.py
accordion_presentation/static/accordion_presentation/css/Field.css
accordion_presentation/static/accordion_presentation/css/accordion_presentation.css
accordion_presentation/static/accordion_presentation/css/fluid_grid.css
accordion_presentation/static/accordion_presentation/js/accordion.js
accordion_presentation/static/accordion_presentation/js/jquery.cycle2.min.js
accordion_presentation/templates/accordion_presentation/accordion.html
accordion_presentation/templates/accordion_presentation/field.html
accordion_presentation/templates/accordion_presentation/plugin.html