Metadata-Version: 1.1
Name: accordion-presentation
Version: 1.0.1
Summary: It is a simple horizontal accordion for django cms
Home-page: http://github.com/luisza/accordion_presentation
Author: Luisza
Author-email: luisza14@gmail.com
License: GPLv2
Keywords: tab django cms django-cms plugin
Platform: UNKNOWN
Classifier: Development Status :: 4 - Beta
Classifier: Environment :: Web Environment
Classifier: Intended Audience :: Developers
Classifier: License :: OSI Approved :: GNU General Public License v2 (GPLv2)
Classifier: Operating System :: OS Independent
Classifier: Programming Language :: Python
Classifier: Framework :: Django
